gocept.bbissues-0.10-py3.8-nspkg.pth
gocept/bbissues/__init__.py
gocept/bbissues/bbissues.py
gocept/bbissues/index.jj2
gocept/bbissues/issues.cfg
gocept/bbissues/tests/__init__.py
gocept/bbissues/tests/conftest.py
gocept/bbissues/tests/test_bbissues.py
gocept/bbissues/tests/testing.cfg
gocept.bbissues-0.10.data/data/COPYRIGHT.txt
gocept.bbissues-0.10.data/data/LICENSE.txt
gocept.bbissues-0.10.dist-info/LICENSE.txt
gocept.bbissues-0.10.dist-info/METADATA
gocept.bbissues-0.10.dist-info/WHEEL
gocept.bbissues-0.10.dist-info/entry_points.txt
gocept.bbissues-0.10.dist-info/namespace_packages.txt
gocept.bbissues-0.10.dist-info/top_level.txt
gocept.bbissues-0.10.dist-info/RECORD
