Metadata-Version: 2.1
Name: gocept.bbissues
Version: 0.10
Summary: Collect issues from multiple repositories and generate a nice html page.
Home-page: https://github.com/gocept/gocept.bbissues
Author: gocept <mail@gocept.com>
Author-email: mail@gocept.com
License: ZPL 2.1
Platform: UNKNOWN
Classifier: Development Status :: 7 - Inactive
Classifier: License :: OSI Approved :: Zope Public License
Classifier: Programming Language :: Python
Classifier: Programming Language :: Python :: 3 :: Only
Classifier: Programming Language :: Python :: 3
Classifier: Programming Language :: Python :: 3.6
Classifier: Programming Language :: Python :: 3.7
Classifier: Programming Language :: Python :: 3.8
License-File: LICENSE.txt
Requires-Dist: jinja2
Requires-Dist: python-dateutil
Requires-Dist: requests
Requires-Dist: setuptools
Provides-Extra: test
